<?xml version="1.0"?>
<!--
SPDX-FileCopyrightText: 2020-2021 National University of Entre Rios (UNER)
SPDX-FileCopyrightText: 2020 Mario Puntin <mario@silix.com.ar>
SPDX-FileCopyrightText: 2020-2022 Luis Falcón <falcon@gnuhealth.org>
SPDX-FileCopyrightText: 2020-2022 GNU Solidario <health@gnusolidario.org>

SPDX-License-Identifier: GPL-3.0-or-later
-->

<tree editable="1">
    <field name="tooth"/>
    <field name="procedure"/>
    <field name="root"/>
    <field name="occlusal"/>
    <field name="vestibular"/>
    <field name="lingual"/>
    <field name="mesial"/>
    <field name="distal"/>
</tree>
